needlefinder/README.MD
needlefinder/__init__.py
needlefinder/requirements.txt
needlefinder/thirdparty.json
needlefinder-0.11.dist-info/LICENSE.rst
needlefinder-0.11.dist-info/METADATA
needlefinder-0.11.dist-info/WHEEL
needlefinder-0.11.dist-info/top_level.txt
needlefinder-0.11.dist-info/RECORD
