Metadata-Version: 2.1
Name: needlefinder
Version: 0.11
Summary: Find occurrences of a needle image in a haystack image using multiprocessing and template matching.
Home-page: https://github.com/hansalemaos/needlefinder
Author: Johannes Fischer
Author-email: aulasparticularesdealemaosp@gmail.com
License: MIT
Keywords: multiprocessing,template,matching,rgb
Classifier: Development Status :: 4 - Beta
Classifier: Programming Language :: Python :: 3 :: Only
Classifier: Programming Language :: Python :: 3.10
Classifier: Topic :: Software Development :: Libraries :: Python Modules
Classifier: Topic :: Utilities
License-File: LICENSE.rst
Requires-Dist: a-cv2-easy-resize
Requires-Dist: a-cv-imwrite-imread-plus
Requires-Dist: a-pandas-ex-apply-ignore-exceptions
Requires-Dist: multiprocca
Requires-Dist: numexpr
Requires-Dist: numpy
Requires-Dist: numpydoc
Requires-Dist: opencv-python
Requires-Dist: pandas
Requires-Dist: pyFFTW
Requires-Dist: scipy
